{
	"partitions" : [
		{
			"name" : "Top",
			"pins" : [
				{
					"name" : "fifo_occu_in[0]",
					"strict" : false
				},
				{
					"name" : "fifo_occu_in[1]",
					"strict" : false
				},
				{
					"name" : "fifo_occu_in[2]",
					"strict" : false
				},
				{
					"name" : "fifo_occu_in[3]",
					"strict" : false
				},
				{
					"name" : "fifo_occu_in[4]",
					"strict" : false
				},
				{
					"name" : "fifo_occu_out[0]",
					"strict" : false
				},
				{
					"name" : "fifo_occu_out[1]",
					"strict" : false
				},
				{
					"name" : "fifo_occu_out[2]",
					"strict" : false
				},
				{
					"name" : "fifo_occu_out[3]",
					"strict" : false
				},
				{
					"name" : "fifo_occu_out[4]",
					"strict" : false
				},
				{
					"name" : "wclk",
					"strict" : false
				},
				{
					"name" : "reset",
					"strict" : false
				},
				{
					"name" : "write_enable",
					"strict" : false
				},
				{
					"name" : "rclk",
					"strict" : false
				},
				{
					"name" : "read_enable",
					"strict" : false
				}
			]
		}
	]
}